restless/__init__.py
restless/errors.py
restless/openapi.py
restless/parameters.py
restless/security.py
restless/util.py
restless/interfaces/__init__.py
restless/interfaces/aws.py
restless/interfaces/azure.py
restless/interfaces/flask_app.py
restless_cloud-0.1.1.dist-info/LICENSE
restless_cloud-0.1.1.dist-info/METADATA
restless_cloud-0.1.1.dist-info/WHEEL
restless_cloud-0.1.1.dist-info/top_level.txt
restless_cloud-0.1.1.dist-info/RECORD
