Metadata-Version: 2.1
Name: restless-cloud
Version: 0.1.1
Summary: A router for AWS Lambda and Azure Functions
Home-page: UNKNOWN
Author: Joaquim Ventura
Author-email: allaphor@gmail.com
License: UNKNOWN
Platform: UNKNOWN
License-File: LICENSE
Requires-Dist: jsonschema
Requires-Dist: pydantic
Provides-Extra: all
Requires-Dist: flask ; extra == 'all'
Requires-Dist: deepdiff ; extra == 'all'
Requires-Dist: pyyaml ; extra == 'all'
Requires-Dist: azure-functions ; extra == 'all'
Requires-Dist: requests ; extra == 'all'
Provides-Extra: azure
Requires-Dist: azure-functions ; extra == 'azure'
Provides-Extra: flask
Requires-Dist: flask ; extra == 'flask'
Provides-Extra: spec
Requires-Dist: pyyaml ; extra == 'spec'
Provides-Extra: tests
Requires-Dist: requests ; extra == 'tests'
Requires-Dist: deepdiff ; extra == 'tests'
